hrpdrebin/__init__.py
hrpdrebin/customui.py
hrpdrebin/maincmd.py
hrpdrebin/mainui.py
hrpdrebin/mythen.py
hrpdrebin/mythenui.py
hrpdrebin/processed.py
hrpdrebin/rangeui.py
rebin/__init__.py
rebin/customui.py
rebin/maincmd.py
rebin/mainui.py
rebin/mythen.py
rebin/mythenui.py
rebin/processed.py
rebin/rangeui.py
hrpdrebin-1.1.dist-info/LICENSE
hrpdrebin-1.1.dist-info/METADATA
hrpdrebin-1.1.dist-info/WHEEL
hrpdrebin-1.1.dist-info/entry_points.txt
hrpdrebin-1.1.dist-info/top_level.txt
hrpdrebin-1.1.dist-info/RECORD
